{
  "name": "mpl-uikit",
  "private": false,
  "version": "0.0.2",
  "type": "module",
  "types": "dist/index.d.ts",
  "files": [
    "dist"
  ],
  "main": "./dist/mpl-uikit.umd.cjs",
  "module": "./dist/mpl-uikit.js",
  "exports": {
    ".": {
      "import": "./dist/mpl-uikit.js",
      "require": "./dist/mpl-uikit.umd.cjs",
      "types": "./dist/index.d.ts"
    }
  },
  "publishConfig": {
    "access": "public"
  },
  "scripts": {
    "dev": "vite",
    "build": "tsc && vite build",
    "lint": "eslint . --ext ts,tsx --report-unused-disable-directives --max-warnings 0",
    "preview": "vite preview"
  },
  "dependencies": {
    "react": "^18.2.0",
    "react-dom": "^18.2.0"
  },
  "devDependencies": {
    "@react-aria/accordion": "^3.0.0-alpha.20",
    "@react-aria/i18n": "^3.8.1",
    "@react-aria/overlays": "^3.16.0",
    "@react-aria/utils": "^3.19.0",
    "@react-stately/collections": "^3.10.0",
    "@react-stately/tree": "^3.7.1",
    "@react-types/overlays": "^3.8.1",
    "@react-types/shared": "^3.19.0",
    "@types/color": "^3.0.4",
    "@types/flat": "^5.0.2",
    "@types/lodash.foreach": "^4.5.7",
    "@types/lodash.get": "^4.4.7",
    "@types/lodash.kebabcase": "^4.1.7",
    "@types/lodash.mapkeys": "^4.6.7",
    "@types/lodash.omit": "^4.5.7",
    "@types/react": "^18.2.15",
    "@types/react-dom": "^18.2.7",
    "@typescript-eslint/eslint-plugin": "^6.0.0",
    "@typescript-eslint/parser": "^6.0.0",
    "@vitejs/plugin-react-swc": "^3.3.2",
    "autoprefixer": "^10.4.15",
    "color": "^4.2.3",
    "color2k": "^2.0.2",
    "deepmerge": "^4.3.1",
    "eslint": "^8.45.0",
    "eslint-plugin-react-hooks": "^4.6.0",
    "eslint-plugin-react-refresh": "^0.4.3",
    "flat": "^5.0.2",
    "framer-motion": "^10.16.4",
    "lodash.foreach": "^4.5.0",
    "lodash.get": "^4.4.2",
    "lodash.kebabcase": "^4.1.1",
    "lodash.mapkeys": "^4.6.0",
    "lodash.omit": "^4.5.0",
    "postcss": "^8.4.29",
    "tailwind-variants": "^0.1.14",
    "tailwindcss": "^3.3.3",
    "typescript": "^5.0.2",
    "vite": "^4.4.5",
    "vite-plugin-dts": "^3.5.3"
  }
}
